classproperty.py
classproperty.txt
setup.py
classproperty.egg-info/PKG-INFO
classproperty.egg-info/SOURCES.txt
classproperty.egg-info/dependency_links.txt
classproperty.egg-info/top_level.txt
