Metadata-Version: 1.0
Name: classproperty
Version: 1.0
Summary: Class properties
Home-page: http://www.z3lab.org/sections/blogs/philipp-weitershausen/2006_05_29_pycon-06-lightning-talk
Author: Philipp von Weitershausen
Author-email: philipp@weitershausen.de
License: ZPL
Download-URL: http://codespeak.net/svn/user/philikon/classproperty#egg=classproperty-dev
Platform: UNKNOWN
